rl_problems/Bandit_Problem/__init__.py
rl_problems/Bandit_Problem/contextual_bandit.py
rl_problems/Bandit_Problem/epsilon_decreasing.py
rl_problems/Bandit_Problem/k_armed_bandit.py
rl_problems/Bandit_Problem/linear_decreasing.py
rl_problems/Bandit_Problem/ucb_algorithm.py
rl_problems-0.1.1.dist-info/METADATA
rl_problems-0.1.1.dist-info/WHEEL
rl_problems-0.1.1.dist-info/top_level.txt
rl_problems-0.1.1.dist-info/RECORD
