Metadata-Version: 2.4
Name: rl-problems
Version: 0.1.1
Summary: Implementations and experiments for classic reinforcement learning problems, including multi-armed bandits, epsilon-greedy strategies, and other RL algorithms for learning and evaluation.
Requires-Python: >=3.12
Requires-Dist: numpy>=1.26.4
